[
    {
        "course": "accounts",
        "institution": "jamb",
        "order": 1,
        "year": 2018,
        "question": "<img src=\"https://myschool.ng/storage/classroom/mQLyi3M5KkI8imwxf05qJE9IuGqB3MoUO9LoLRFB.jpeg\" class=\"img-fluid\">",
        "explanation": "<div class=\"mb-4\">\n<img src=\"https://myschool.ng/storage/classroom_answers/S4P71YUCB14KS2B4qcDlnIiMmHOjs0NmQqBv5wm3.jpeg\" class=\"img-fluid\">\n</div><p>Capital Employed is the difference between the total assets and current liabilities of the company</p>",
        "correctIndex": 3,
        "options": [
            "₦7000",
            "₦10000",
            "₦22000",
            "₦15000"
        ],
        "type": "objectives"
    },
    {
        "course": "accounts",
        "institution": "jamb",
        "order": 2,
        "year": 2018,
        "question": "<p>Advertising expenses incurred on a product in a business organization should be charged to</p>",
        "explanation": "<p>Advertising expenses are expenses incurred in order to enhance the sales of the company’s product/services</p>",
        "correctIndex": 0,
        "options": [
            "Sales department",
            "Production department",
            "Purchase department",
            "Administration department"
        ],
        "type": "objectives"
    },
    {
        "course": "accounts",
        "institution": "jamb",
        "order": 3,
        "year": 2018,
        "question": "<table border=\"1\" cellpadding=\"1\" cellspacing=\"1\" style=\"width:500px\">\n<tbody>\n<tr>\n<td>                                      N</td>\n<td>                             N</td>\n</tr>\n<tr>\n<td>Capital                                         39,000</td>\n<td> Land  20,000</td>\n</tr>\n<tr>\n<td>Long Term Loan      15, 000                   </td>\n<td>Building 30,000</td>\n</tr>\n<tr>\n<td>Creditors                                       9,000</td>\n<td>Stock  40,000</td>\n</tr>\n<tr>\n<td> </td>\n<td>Debtors  6,000</td>\n</tr>\n<tr>\n<td>Accrued wages                             5,000</td>\n<td>Cash  8, 000</td>\n</tr>\n<tr>\n<td>                       68,000</td>\n<td>   68,000</td>\n</tr>\n</tbody>\n</table><p> </p><p> </p><p> </p><p>Use the information above to answer the question</p><p> : The acid test ratio in the company is___________</p><p> </p><p> </p><p> </p><p> </p>",
        "explanation": "<p>Acid test ratio measures the liquidity position of a company after deduction stock (inventory) from current assets</p><p>  Formula: current assets less inventory/current liabilities</p><p>  18000 - 4000/14000 = 1 : 1</p>",
        "correctIndex": 0,
        "options": [
            "1:1",
            "2:3",
            "1:2",
            "3:2"
        ],
        "type": "objectives"
    },
    {
        "course": "accounts",
        "institution": "jamb",
        "order": 4,
        "year": 2018,
        "question": "<p>When goods are sent to branch at cost plus mark up, it means that the branch should sell at_____________</p>",
        "explanation": "<p>Cost plus mark up is a pricing strategy in which the selling price is determined by adding a specific amount mark up to a product unit cost</p>",
        "correctIndex": 0,
        "options": [
            "Price above or below the stipulated price",
            "Any price but not below the transfer price",
            "Cost price",
            "A price that is equal to the mark up"
        ],
        "type": "objectives"
    },
    {
        "course": "accounts",
        "institution": "jamb",
        "order": 5,
        "year": 2018,
        "question": "<p>The office responsible for ascertaining whether all public expenditures and appropriations are in line with approved guidelines is the________</p>",
        "explanation": "<p>Appropriation is the amount that government reserves for a particular purpose. Public expenditure is the spending made by government of a country on collective needs</p>",
        "correctIndex": 2,
        "options": [
            "Accountant general",
            "Finance minister",
            "Auditor general",
            "Permanent secretory."
        ],
        "type": "objectives"
    },
    {
        "course": "accounts",
        "institution": "jamb",
        "order": 6,
        "year": 2018,
        "question": "<p>Use the information below to answer question</p><p> <br>\nTrading account for the year ended 31st December 2009</p><p> </p><table border=\"1\" cellpadding=\"1\" cellspacing=\"1\" style=\"width:500px\">\n<tbody>\n<tr>\n<td>₦</td>\n<td>₦</td>\n</tr>\n<tr>\n<td>Opening Stock                                               32,000</td>\n<td>Sales                48,000     </td>\n</tr>\n<tr>\n<td>Purchases                           40,000</td>\n<td>Less Return       2,000</td>\n</tr>\n<tr>\n<td>Carriage inwards                   1,000</td>\n<td> </td>\n</tr>\n<tr>\n<td>                                           <strong> 41,000</strong></td>\n<td> </td>\n</tr>\n<tr>\n<td>Less Return                          2,000                 39,000</td>\n<td> </td>\n</tr>\n<tr>\n<td> </td>\n<td> </td>\n</tr>\n<tr>\n<td>Cost of goods available                                     ??</td>\n<td> </td>\n</tr>\n<tr>\n<td>Less closing stock                                          <strong>  9,000</strong></td>\n<td> </td>\n</tr>\n<tr>\n<td>Cost of goods sold                                            ??</td>\n<td> </td>\n</tr>\n</tbody>\n</table><p> </p>",
        "explanation": "<p>Average stock is the calculating the addition of stock at the beginning and at the end of the financial period and dividing the value by two.</p><p>  It is the average value of products kept for sale during an accounting period.</p><p>  Therefore:</p><p>  Average stock = opening stock + closing stock/2</p><p>  = 32000 + 9000/2</p><p>  = 41000/2</p><p>  =₦ 20500</p>",
        "correctIndex": 0,
        "options": [
            "#20,500",
            "#23,000",
            "#28,000",
            "#27,000"
        ],
        "type": "objectives"
    },
    {
        "course": "accounts",
        "institution": "jamb",
        "order": 7,
        "year": 2018,
        "question": "<p>Use the information below to answer question</p><p> <br>\nTrading account for the year ended 31st December 2009</p><table border=\"1\" cellpadding=\"1\" cellspacing=\"1\">\n<tbody>\n<tr>\n<td>₦</td>\n<td>₦</td>\n</tr>\n<tr>\n<td>Opening Stock                                               32,000</td>\n<td>Sales                48,000     </td>\n</tr>\n<tr>\n<td>Purchases                           40,000</td>\n<td>Less Return       2,000</td>\n</tr>\n<tr>\n<td>Carriage inwards                   1,000</td>\n<td> </td>\n</tr>\n<tr>\n<td>                                           <strong> 41,000</strong></td>\n<td> </td>\n</tr>\n<tr>\n<td>Less Return                          2,000                 39,000</td>\n<td> </td>\n</tr>\n<tr>\n<td> </td>\n<td> </td>\n</tr>\n<tr>\n<td>Cost of goods available                                     ??</td>\n<td> </td>\n</tr>\n<tr>\n<td>Less closing stock                                          <strong>  9,000</strong></td>\n<td> </td>\n</tr>\n<tr>\n<td>Cost of goods sold                                            ??</td>\n<td> </td>\n</tr>\n</tbody>\n</table><p> </p><p>Calculate the cost of goods sold</p>",
        "explanation": "<p>Cost of goods sold is the direct costs attributable to the production of the goods sold in a company.</p><p>  Cost of goods available for sale (32000 + 39000) = 71000</p><p>  Less closing stock = 9000</p><p>  Cost of goods sold = 7100 - 9000</p><p> = 62000</p>",
        "correctIndex": 1,
        "options": [
            "#61,000",
            "#62,000",
            "#58,000",
            "#57,000"
        ],
        "type": "objectives"
    },
    {
        "course": "accounts",
        "institution": "jamb",
        "order": 8,
        "year": 2018,
        "question": "<p>The amount called in respect of a share but not paid before or on the date fixed for payment is referred to as:</p>",
        "explanation": "<p>is the amount called by the company which is not paid by the shareholders before the due date fixed for payment</p>",
        "correctIndex": 1,
        "options": [
            "Call in advance",
            "call in arrears",
            "forfeiture",
            "shares"
        ],
        "type": "objectives"
    },
    {
        "course": "accounts",
        "institution": "jamb",
        "order": 9,
        "year": 2018,
        "question": "<p>When goodwill is not retained in the business, the entries in the new partners books will be to debit______________</p>",
        "explanation": "<p>When goodwill is raised in the books at full value, the entry is</p><p>  Dr Goodwill Account</p><p>  Cr Old partners capital account (old ratio)</p><p>  When the raised goodwill is written off, entry will be:</p><p>  Dr All partners capital account</p><p>  Cr Goodwill accounts</p><p>  Note: goodwill written off includes new partners in the new profit sharing ratio</p>",
        "correctIndex": 3,
        "options": [
            "Goodwill account and credit partners capital account",
            "Cash account and credit goodwill account",
            "Goodwill account and credit cash account",
            "Partners capital account and credit goodwill account"
        ],
        "type": "objectives"
    },
    {
        "course": "accounts",
        "institution": "jamb",
        "order": 10,
        "year": 2018,
        "question": "<p>Use the information below to answer the question</p><p> </p><table border=\"1\" cellpadding=\"1\" cellspacing=\"1\">\n<tbody>\n<tr>\n<td><strong>Liabilities                     ₦</strong></td>\n<td><strong>Assets                                   ₦</strong></td>\n</tr>\n<tr>\n<td>Capital                        40,000         </td>\n<td>Furnishing                               10,000</td>\n</tr>\n<tr>\n<td> </td>\n<td>Ceiling Fan                               1,500</td>\n</tr>\n<tr>\n<td> </td>\n<td>Cash in Hand                         28,500</td>\n</tr>\n<tr>\n<td><strong>                                    40,000</strong></td>\n<td>                                               <strong>40,000</strong></td>\n</tr>\n</tbody>\n</table><p> </p><p>If at 31/1/95 the following information was ascertained</p><p> </p><p>  (i). rent for shop #12,000 paid for the year</p><p>  (ii). Total purchases #15,000</p><p>  (iii). Total sales #8,200</p><p>  (iv). Stock of goods left #10,000</p><p>  (v). paid sales boy #500</p>",
        "explanation": "<div class=\"mb-4\">\n<img src=\"https://myschool.ng/storage/classroom_answers/Kr3ABcZpEhOvsP0AJRFw7MZIxpbM1qBa58UlWNiw.jpeg\" class=\"img-fluid\">\n</div><p>Trading, profit and loss account for the month ended 31/1/95</p><p> </p><p>For the month ended 31/1/95</p><p>                                                                ₦                             ₦</p><p>Sales                                                                                      8200</p><p>Cost of sales:</p><p>Purchases                                           15000</p><p>Closing stock                                      (10000)                (5000)  </p><p>Gross profit                                                                        <strong>8200</strong></p><p>Gross profit b/d                                                                8200</p><p>Sales commission                             500</p><p>Rent                                                    1000                     (1500)</p><p>Net profit                                                                            <strong>1700</strong></p><p>WORKINGS:</p><p>Rent paid for 12 months                                                   12000</p><p>Rent paid for one month</p><p>12000 x 1/12                                                                      (1000)</p><p>Prepaid rent                                                                       <strong>11000</strong></p><p>Balance sheet as at 31/1/95                                                                                                                                                                                                                                                       </p><p>Noncurrent asset:                                                           </p><p>Furnishing                                           10000</p><p>Ceiling fan                                           1500                      11500</p><p>Current asset:</p><p>Cash (see cash account)                     9200</p><p>Inventory                                             10000 </p><p>Prepaid rent (see above)                    11000                          30200   </p><p>                                                                                               41700</p><p>Capital                                                                                    40000</p><p>Net profit (see p&amp;l)                                                                  1,700                                    </p><p>                                                                                                41700</p>",
        "correctIndex": 2,
        "options": [
            "#40,000",
            "#41,500",
            "#41,700",
            "48,500"
        ],
        "type": "objectives"
    },
    {
        "course": "accounts",
        "institution": "jamb",
        "order": 11,
        "year": 2018,
        "question": "<p>In the head office ledger, the value of goods sent to the branch are____________</p>",
        "explanation": "<p>Branch current account is maintained in the head office books to record all transactions between the head office and the branch. This account is debited with the following:</p><p>  i. Goods sent to branch</p><p>  ii. Expenses of the branch paid by the head office</p><p>  iii. Profit of the branch</p>",
        "correctIndex": 1,
        "options": [
            "Debited to the branch current account",
            "Debited to the head office current account",
            "Credited to the head office current account",
            "Credited to the branch current account"
        ],
        "type": "objectives"
    },
    {
        "course": "accounts",
        "institution": "jamb",
        "order": 12,
        "year": 2018,
        "question": "<p>If the purchase price exceeds the net assets of a company, the excess amount is debited to________________</p>",
        "explanation": "<p>Goodwill is the excess of purchase consideration over the total value of the business</p>",
        "correctIndex": 2,
        "options": [
            "Cash account",
            "purchase account",
            "goodwill account",
            "sales account"
        ],
        "type": "objectives"
    },
    {
        "course": "accounts",
        "institution": "jamb",
        "order": 13,
        "year": 2018,
        "question": "<p>Gross profit in the branch adjustment account is transferred to the branch____________</p>",
        "explanation": "<p>records profit on branch account</p>",
        "correctIndex": 1,
        "options": [
            "Income and expenditure account",
            "profit and loss account",
            "receipt and payment account",
            "trading account"
        ],
        "type": "objectives"
    },
    {
        "course": "accounts",
        "institution": "jamb",
        "order": 14,
        "year": 2018,
        "question": "<p>Ade, Tony, Rose share profit and losses in the ratio of 3 : 2 : 1 respectively. Ade retires and the remaining partners decide to take Ade’s share in the existing ratio. What is the new ratio?</p>",
        "explanation": "<p>The existing ratio between Tony and Rose = 2/6 and 1/6</p><p>  Ade’s ratio = 3/6</p><p>  Ade’s share to be taken by Tony and Rose in the ratio 2 : 1</p><p>  Tony gets: 3/6 x 2/6</p><p>  = 6/18</p><p>  Rose gets: 3/6 x 1/3</p><p>  = 3/18</p><p>  New ratio between Tony and Rose = 6 : 3</p><p>  = 2 : 1</p>",
        "correctIndex": 2,
        "options": [
            "1 : 1",
            "3 : 6",
            "2 : 1",
            "2 : 6"
        ],
        "type": "objectives"
    },
    {
        "course": "accounts",
        "institution": "jamb",
        "order": 15,
        "year": 2018,
        "question": "<p>Calls in advance are treated in the balance sheet as_______</p>",
        "explanation": "<p>calls in advance is treated as a current liability until the calls are made and the amount actually becomes payable by the shareholders</p>",
        "correctIndex": 2,
        "options": [
            "Current asset",
            "Fixed asset",
            "Current liability",
            "Fixed liability"
        ],
        "type": "objectives"
    },
    {
        "course": "accounts",
        "institution": "jamb",
        "order": 16,
        "year": 2018,
        "question": "<p>Why are adjustments in the profit and loss account necessary?</p>",
        "explanation": "<p>Fundamental principle of preparing P&amp;L account is that expenses and income relating to only the trading period are taken to the trading profit and loss account.</p>",
        "correctIndex": 3,
        "options": [
            "To cover some expenses of the following year",
            "To show the provisions made during the year",
            "To show the total expenses paid and income received during the year",
            "To ascertain the actual expenses incurred and income earned during the year"
        ],
        "type": "objectives"
    },
    {
        "course": "accounts",
        "institution": "jamb",
        "order": 17,
        "year": 2018,
        "question": "<p>Which of the following is not a type of branch?</p>",
        "explanation": null,
        "correctIndex": 3,
        "options": [
            "Dependent branch",
            "foreign branch",
            "independent branch",
            "single branch"
        ],
        "type": "objectives"
    },
    {
        "course": "accounts",
        "institution": "jamb",
        "order": 18,
        "year": 2018,
        "question": "<p>In reconciling the branch and head office accounts, remittance in transit in the branch books is treated as a_____________</p>",
        "explanation": "<p>A contra entry is an entry which is recorded to reverse or offset an entry on the other side of an account</p><p>  When cash is remitted from the branch</p><p>  Dr Bank account</p><p>  Cr Branch account</p><p>  Or</p><p>  Dr Remittance from bank</p><p>  Cr Remittance from branch</p>",
        "correctIndex": 0,
        "options": [
            "Debit entry",
            "Contra entry",
            "Credit entry",
            "Reversal entry"
        ],
        "type": "objectives"
    },
    {
        "course": "accounts",
        "institution": "jamb",
        "order": 19,
        "year": 2018,
        "question": "<p>Profit or loss in a partnership is usually arrived at after deducting from gross profit all expenses including____________</p>",
        "explanation": "<p>is charged in the profit and loss account as finance expenses</p>",
        "correctIndex": 2,
        "options": [
            "Partners salaries",
            "Interest on capital",
            "Interest on loans",
            "Partners drawings"
        ],
        "type": "objectives"
    },
    {
        "course": "accounts",
        "institution": "jamb",
        "order": 20,
        "year": 2018,
        "question": "<p>Use the information below to answer the question</p><p> </p><table border=\"1\" cellpadding=\"1\" cellspacing=\"1\">\n<tbody>\n<tr>\n<td><strong>Liabilities                     ₦</strong></td>\n<td><strong>Assets                                   ₦</strong></td>\n</tr>\n<tr>\n<td>Capital                        40,000         </td>\n<td>Furnishing                               10,000</td>\n</tr>\n<tr>\n<td> </td>\n<td>Ceiling Fan                               1,500</td>\n</tr>\n<tr>\n<td> </td>\n<td>Cash in Hand                         28,500</td>\n</tr>\n<tr>\n<td><strong>                                    40,000</strong></td>\n<td>                                               <strong>40,000</strong></td>\n</tr>\n</tbody>\n</table><p> </p><p>If at 31/1/95 the following information was ascertained;</p><p>  (i). rent for shop #12,000 paid for the year</p><p>  (ii). Total purchases #15,000</p><p>  (iii). Total sales #8,200</p><p>  (iv). Stock of goods left #10,000</p><p>  (v). paid sales boy #500</p><p> </p><p>If at 31/1/95 the following information was ascertained;</p><p>  (i). rent for shop #12,000 paid for the year</p><p>  (ii). Total purchases #15,000</p><p>  (iii). Total sales #8,200</p><p>  (iv). Stock of goods left #10,000</p><p>  (v). paid sales boy #500</p><p> </p><p>  What is the balance on its cash account as at 31/1/95</p>",
        "explanation": null,
        "correctIndex": 1,
        "options": [
            "#22,800",
            "#9,200",
            "#800",
            "#21,200"
        ],
        "type": "objectives"
    },
    {
        "course": "accounts",
        "institution": "jamb",
        "order": 21,
        "year": 2018,
        "question": "<p>The amount paid by the new partner on admission as a compensation for the reputation built up by old partners is a</p>",
        "explanation": "<p>Goodwill is the excess of the purchase consideration over the total value of an entity</p>",
        "correctIndex": 1,
        "options": [
            "Bonus",
            "Good will",
            "Premium",
            "Commission"
        ],
        "type": "objectives"
    },
    {
        "course": "accounts",
        "institution": "jamb",
        "order": 22,
        "year": 2018,
        "question": "<table border=\"1\" cellpadding=\"1\" cellspacing=\"1\">\n<tbody>\n<tr>\n<td> </td>\n<td> <s>N</s></td>\n</tr>\n<tr>\n<td>\n<p>Stock at branch 1st January at cost </p>\n</td>\n<td>400</td>\n</tr>\n<tr>\n<td>\n<p>Goods sent to branch at cost</p>\n</td>\n<td>     8000</td>\n</tr>\n<tr>\n<td>\n<p>Returns to head office</p>\n</td>\n<td>            340           </td>\n</tr>\n<tr>\n<td>\n<p>Cash sales</p>\n</td>\n<td>9160</td>\n</tr>\n<tr>\n<td>\n<p>Stock at branch 31st December at cost</p>\n</td>\n<td>720</td>\n</tr>\n</tbody>\n</table><p> </p><p>Use the information below to answer the question.</p><p>  Adex Ltd. Issues stock to its retail branches at cost price. The following particulars relate to Ede branch.</p>",
        "explanation": null,
        "correctIndex": 3,
        "options": [
            "#1870",
            "#1530",
            "#1640",
            "#1820"
        ],
        "type": "objectives"
    },
    {
        "course": "accounts",
        "institution": "jamb",
        "order": 23,
        "year": 2018,
        "question": "<p>Which of the following methods of invoicing goods to branches facilitate easy checks on the activities of branches?</p>",
        "explanation": "<p>Goods are transferred from head office to branch at cost price, selling price and cost price plus mark up</p>",
        "correctIndex": 2,
        "options": [
            "Selling price",
            "Fixed percentage on cost",
            "Cost price",
            "Invoice price"
        ],
        "type": "objectives"
    },
    {
        "course": "accounts",
        "institution": "jamb",
        "order": 24,
        "year": 2018,
        "question": "<p>When goods are sent to branch at cost plus mark up, it means that the branch should sell at_____________</p>",
        "explanation": "<p>Cost plus mark up is a pricing strategy in which the selling price is determined by adding a specific amount mark up to a product unit cost</p>",
        "correctIndex": 0,
        "options": [
            "Price above or below the stipulated price",
            "Any price but not below the transfer price",
            "Cost price",
            "A price that is equal to the mark up"
        ],
        "type": "objectives"
    },
    {
        "course": "accounts",
        "institution": "jamb",
        "order": 25,
        "year": 2018,
        "question": "<p>In departmental accounting, which is not a transfer pricing_________</p>",
        "explanation": null,
        "correctIndex": 3,
        "options": [
            "cost based transfer price",
            "market based transfer pricing",
            "Dual pricing system",
            "peak pricing"
        ],
        "type": "objectives"
    },
    {
        "course": "accounts",
        "institution": "jamb",
        "order": 26,
        "year": 2018,
        "question": "<p>What act generally includes completing unfinished partnership business, collecting and paying debts, collecting partnership assets to be turned into cash and taking inventory?</p>",
        "explanation": "<p>It is the first step in termination process</p>",
        "correctIndex": 1,
        "options": [
            "Formation",
            "dissolution",
            "winding up",
            "termination"
        ],
        "type": "objectives"
    },
    {
        "course": "accounts",
        "institution": "jamb",
        "order": 27,
        "year": 2018,
        "question": "<p>Using the following:</p><p>  Balance as par overdraft of the cashbook is ₦4000 ,uncredited cheque is ₦2300, bank charges ₦300, unpresented cheque ₦5000.</p><p>  what is the adjusted cashbook balance?</p>",
        "explanation": null,
        "correctIndex": 2,
        "options": [
            "4000",
            "300",
            "4300",
            "5000"
        ],
        "type": "objectives"
    },
    {
        "course": "accounts",
        "institution": "jamb",
        "order": 28,
        "year": 2018,
        "question": "<p>Branch stock adjustment account is prepared at?</p>",
        "explanation": "<p>Branch stock adjustment account deals with the loading on the respective items of goods relating to Branch stock account.</p><p>  Branch adjustment account is prepared at invoice price.</p><p>  The difference between the two sides of this account reveals either gross profit (if credit side is greater than the debit side) or gross loss (if debit side is greater than the credit side).</p>",
        "correctIndex": 2,
        "options": [
            "Cost price",
            "new price",
            "invoice price",
            "normal price"
        ],
        "type": "objectives"
    },
    {
        "course": "accounts",
        "institution": "jamb",
        "order": 29,
        "year": 2018,
        "question": "<p>A partnership deed is used to____________</p>",
        "explanation": "<p>Partnership deed can be used to:</p><p>  i. Indicates terms on which the business corporation us founded</p><p>  ii. To form a partnership for the purpose of doing business together</p><p>  iii. Prevent future disputes</p><p>  iv. Promote mutual understanding</p><p>  v. Avoid mistrust</p>",
        "correctIndex": 0,
        "options": [
            "Promote mutual understanding",
            "Enhance mistrust",
            "Encourage discrepancy",
            "Control funds"
        ],
        "type": "objectives"
    },
    {
        "course": "accounts",
        "institution": "jamb",
        "order": 30,
        "year": 2018,
        "question": "<p>The cost price method is applicable when_____</p>",
        "explanation": "<p>cost price method is used to enhance quick sales</p>",
        "correctIndex": 1,
        "options": [
            "Goods are sold at specific prices",
            "goods are perishable",
            "goods attract different gross profit percentage",
            "to disclose gross profit or loss"
        ],
        "type": "objectives"
    },
    {
        "course": "accounts",
        "institution": "jamb",
        "order": 31,
        "year": 2018,
        "question": "<table border=\"1\" cellpadding=\"1\" cellspacing=\"1\">\n<tbody>\n<tr>\n<td> </td>\n<td> <s>N</s></td>\n</tr>\n<tr>\n<td>\n<p>Stock at branch 1st January at cost </p>\n</td>\n<td>400</td>\n</tr>\n<tr>\n<td>\n<p>Goods sent to branch at cost</p>\n</td>\n<td>8000</td>\n</tr>\n<tr>\n<td>\n<p>Returns to head office</p>\n</td>\n<td>340</td>\n</tr>\n<tr>\n<td>\n<p>Cash sales</p>\n</td>\n<td>9160</td>\n</tr>\n<tr>\n<td>\n<p>Stock at branch 31st December at cost</p>\n</td>\n<td>720</td>\n</tr>\n</tbody>\n</table><p> </p><p>Use the information below to answer the question.</p><p>  Adex Ltd. Issues stock to its retail branches at cost price.</p><p> Calculate the cost of goods credited to the head office trading account</p><p> </p>",
        "explanation": null,
        "correctIndex": 3,
        "options": [
            "#7200",
            "#7460",
            "#7500",
            "#7660"
        ],
        "type": "objectives"
    },
    {
        "course": "accounts",
        "institution": "jamb",
        "order": 32,
        "year": 2018,
        "question": "<p>In dealing with incomplete record, fixed assets are posted to___________-</p>",
        "explanation": "<p>fixed asset are brought forward in closing balance sheet</p>",
        "correctIndex": 2,
        "options": [
            "Profit and loss account as brought forward figure",
            "Closing balance sheet as carried forward figure",
            "Closing balance sheet as brought forward figure",
            "Profit and loss as carried forward figure"
        ],
        "type": "objectives"
    },
    {
        "course": "accounts",
        "institution": "jamb",
        "order": 33,
        "year": 2018,
        "question": "<p>Tea and Cup are into a partnership business. Interests on drawings made by partners are at 10% per annum. Tea’s capital is ₦70000 and current balance is ₦50000. He withdrew the following amounts during the year : 3000 on 31st January ,2000 on 31st March, 4000 on 1st July, 1500 on the 30th September, 2500 on 1st November. Cup’s capital is ₦100000 and current balance is ₦40000. He made no drawings during the period. What is the interest on the drawings of Tea?</p>",
        "explanation": null,
        "correctIndex": 0,
        "options": [
            "₦705",
            "₦500",
            "₦1000",
            "₦10000"
        ],
        "type": "objectives"
    },
    {
        "course": "accounts",
        "institution": "jamb",
        "order": 34,
        "year": 2018,
        "question": "<p>Which of the following should not be adjusted for in the profit and loss account?</p>",
        "explanation": "<p>is adjusted for in the income and expenditure account</p>",
        "correctIndex": 2,
        "options": [
            "Accruals",
            "inventory",
            "subscription",
            "depreciation"
        ],
        "type": "objectives"
    },
    {
        "course": "accounts",
        "institution": "jamb",
        "order": 35,
        "year": 2018,
        "question": "<p>Use the information below to answer the question .</p><p> </p><table border=\"1\" cellpadding=\"1\" cellspacing=\"1\">\n<tbody>\n<tr>\n<td> </td>\n<td>Total</td>\n<td>P</td>\n<td>Q</td>\n<td> </td>\n<td>Total</td>\n<td>P</td>\n<td>Q</td>\n</tr>\n<tr>\n<td> </td>\n<td>₦</td>\n<td>₦</td>\n<td>₦</td>\n<td> </td>\n<td>₦</td>\n<td>₦</td>\n<td>₦</td>\n</tr>\n<tr>\n<td>Stock</td>\n<td>3,000</td>\n<td>2,000</td>\n<td>1,000</td>\n<td>Sales</td>\n<td>10,000</td>\n<td>6,000</td>\n<td>4,000</td>\n</tr>\n<tr>\n<td>Purchase</td>\n<td>4,000</td>\n<td>2,500</td>\n<td>1,500</td>\n<td>Closing Stock</td>\n<td>  2,000</td>\n<td>1,500</td>\n<td>   500</td>\n</tr>\n</tbody>\n</table><p> </p><p>Goods worth #300 was transferred from department Q to P. Similarly, P’s total expenses for the period was #200.</p><p>  Department P’s net profit was</p>",
        "explanation": null,
        "correctIndex": 0,
        "options": [
            "#2,500",
            "#2,800",
            "#3,000",
            "#5,200"
        ],
        "type": "objectives"
    },
    {
        "course": "accounts",
        "institution": "jamb",
        "order": 36,
        "year": 2018,
        "question": "<p>In the absence of a partnership deed, the act stipulates that____________</p>",
        "explanation": "<p>Under the Partnership Act, the following rules will be applied in the absence of an agreement among partners:</p><p>  i. Profit or losses of the firm will be shared equally by the partners</p><p>  ii. Interest on capital will not be allowed to any partner.</p><p>  iii. No interest will be charged on drawings</p><p>  iv. Interest on loan will be 6% on the loan</p><p>  v. No salary or remuneration will be allowed to any of the partners</p><p>  vi. Every partner must take part in the management of the partnership business</p><p>  vii. The partnership books are kept at the place of business of the partnership and every partner may have access to and inspect and copy any of them.</p>",
        "correctIndex": 3,
        "options": [
            "An amount should be fixed as salaries for partners",
            "Profits and losses should not be shared equally",
            "Interest on partner’s loan should be 25%",
            "Interest should not be allowed on partners drawings"
        ],
        "type": "objectives"
    },
    {
        "course": "accounts",
        "institution": "jamb",
        "order": 37,
        "year": 2018,
        "question": "<p>A partnership’s internal regulation are set out by________---</p>",
        "explanation": "<p>A partnership deed is a written agreement among the partners specifying rules and regulations and is signed by all the partners and stamped as per stamp act with an aim to prevent possible disputes and disagreements among the partners at future dates</p>",
        "correctIndex": 2,
        "options": [
            "A constitution",
            "A law",
            "A deed",
            "An article"
        ],
        "type": "objectives"
    },
    {
        "course": "accounts",
        "institution": "jamb",
        "order": 38,
        "year": 2018,
        "question": "<p>Sule and Ahmed are in partnership sharing profit and losses equally. If Khadija is admitted as a new partner to take 1/5 th as her share. What is the new profit or loss sharing?</p>",
        "explanation": "<p>If Khadija is to take 1/5th i.e. 20%</p><p>  Sule and Ahmed are to share 80% (100% - 20%) equally</p><p>  Sule = 2/5</p><p>  Ahmed = 2/5</p><p>  Khadija = 1/5</p>",
        "correctIndex": 1,
        "options": [
            "Sule1/3, Ahmed1/3, Khadija 1/3",
            "Sule1/3, Ahmed1/3, Khadija 1/3",
            "Sule1/5, Ahmed1/5, Khadija3/5",
            "Sule2/5, Ahmed1/5, Khadija2/5"
        ],
        "type": "objectives"
    },
    {
        "course": "accounts",
        "institution": "jamb",
        "order": 39,
        "year": 2018,
        "question": "<p>Transfers from the head office to branches are best carried out at__________</p>",
        "explanation": "<p>Goods are transferred from head office to branch at cost price, selling price and cost price plus mark up</p>",
        "correctIndex": 1,
        "options": [
            "Cost price",
            "Cost plus mark up",
            "Selling price",
            "Market price"
        ],
        "type": "objectives"
    },
    {
        "course": "accounts",
        "institution": "jamb",
        "order": 40,
        "year": 2018,
        "question": "<p>Which of the following is a common cause of a discrepancy between head office and branch trial office________</p>",
        "explanation": "<p>Goods in transit are goods sent by the head office to branch but by the close of financial year, these goods have not yet reached the branch.</p><p>  Cash in transit are cash remitted by the branch to head office by the end of the financial year this cash has not yet reached the head office</p><p>  Another major cause of discrepancy is returns in transit. This is the returns by the branch to head office but by the end of the year, they have not been received by the head office</p>",
        "correctIndex": 2,
        "options": [
            "Stock and repayment",
            "Creditors and cash in transit",
            "Stock and cash in transit",
            "Debtors and cash in transit"
        ],
        "type": "objectives"
    },
    {
        "course": "accounts",
        "institution": "jamb",
        "order": 41,
        "year": 2018,
        "question": "<p>Departmentalization of accounts is useful because it shows the____________</p>",
        "explanation": "<p>Departmental accounting is prepared to ensure that the results of each individual department is known</p>",
        "correctIndex": 0,
        "options": [
            "Over all performance of a division",
            "Cost per unit of a profit",
            "Price per unit of a product",
            "Over all performance of a firm"
        ],
        "type": "objectives"
    },
    {
        "course": "accounts",
        "institution": "jamb",
        "order": 42,
        "year": 2018,
        "question": "<p>Why should a new partner contribute towards goodwill on his admission?</p>",
        "explanation": "<p>Goodwill is being paid by a new partner because the partnership he is entering into already has goodwill in the market as well as to pay for the portion sacrificed by existing partners in form to their profit to admit the new partner.</p>",
        "correctIndex": 2,
        "options": [
            "It is a norm",
            "to ensure new partner also have a stake in the business",
            "the firm into which he is entering already has some goodwill in the market",
            "to purchase the business"
        ],
        "type": "objectives"
    },
    {
        "course": "accounts",
        "institution": "jamb",
        "order": 43,
        "year": 2018,
        "question": "<p>The rent expense for Trendy store is ₦3500. Trendy store has three departments; jewelry, hair dressing, and clothing. The floor spaces occupied by the departments are 3:2:5 respectively. What is the rent allocated to clothing department?</p>",
        "explanation": "<p>Jewelry 3/10 x 3500 = 1050</p><p>  Hairdressing 2/10 x 3500 = 700</p><p>  Clothing 5/10 x 3500 = 1750</p>",
        "correctIndex": 2,
        "options": [
            "₦700",
            "₦1050",
            "₦1750",
            "₦3500"
        ],
        "type": "objectives"
    },
    {
        "course": "accounts",
        "institution": "jamb",
        "order": 44,
        "year": 2018,
        "question": "<p>Cost of rent as an expense can be apportioned to all department on the basis of:</p>",
        "explanation": "<p>Indirect expenses are allocated among departments in order to ascertain the profits or loss made by each department</p>",
        "correctIndex": 2,
        "options": [
            "No of employees",
            "stock value",
            "space occupied",
            "wages"
        ],
        "type": "objectives"
    },
    {
        "course": "accounts",
        "institution": "jamb",
        "order": 46,
        "year": 2018,
        "question": "<p>Which of the following is a conversion cost?</p>",
        "explanation": "<p>Conversion costs are costs required to convert raw materials into finished goods</p><p>  Formula for conversion cost= direct labor+ factory overheads</p>",
        "correctIndex": 0,
        "options": [
            "Factory overhead",
            "purchases",
            "material cost",
            "wages"
        ],
        "type": "objectives"
    },
    {
        "course": "accounts",
        "institution": "jamb",
        "order": 47,
        "year": 2018,
        "question": "<p>Tea and Cup are into a partnership business. Interests on drawings made by partners are at 10% per annum. Tea’s capital is ₦70000 and current balance is ₦50000. He withdrew the following amounts during the year : 3000 on 31st January , 2000 on 31st March, 4000 on 1st July, 1500 on the 30th September, 2500 on 1st November. Cup’s capital is ₦100000 and current balance is ₦40000. He made no drawings during the period. what is the closing balance in Tea’s current account</p>",
        "explanation": "<div class=\"mb-4\">\n<img src=\"https://myschool.ng/storage/classroom_answers/PR33biPo6VQ1F2Xzkz1UmnIkbKiVOxurRTwQkJ3s.jpeg\" class=\"img-fluid\">\n</div><p>Drawings: 3000 + 2000 + 4000 + 1500 + 2500 = 13000</p>",
        "correctIndex": 0,
        "options": [
            "36,925Cr",
            "40,000Cr",
            "50,000Dr",
            "36,295Dr"
        ],
        "type": "objectives"
    },
    {
        "course": "accounts",
        "institution": "jamb",
        "order": 48,
        "year": 2018,
        "question": "<p>To account for expenses paid by head office on behalf of the branch, the branch should___________</p>",
        "explanation": "<p>The head office maintains a book, (branch account) more or less like other personal accounts, so that any expenses incurred on behalf of the branch will also be debited to the branch account. Similarly, in the branch books, there will be head office accounts</p>",
        "correctIndex": 0,
        "options": [
            "Debit profit and loss account and credit head office account",
            "Debit head office account and credit cash",
            "Credit cash and debit profit and loss account",
            "Credit profit and loss account and debit head office account"
        ],
        "type": "objectives"
    },
    {
        "course": "accounts",
        "institution": "jamb",
        "order": 49,
        "year": 2018,
        "question": "<p>Use the information below to answer the question.</p><p>  Calculate the balance in the bank statement.</p><table border=\"1\" cellpadding=\"1\" cellspacing=\"1\">\n<tbody>\n<tr>\n<td> </td>\n<td>₦</td>\n</tr>\n<tr>\n<td>\n<p>Balance as per cashbook</p>\n</td>\n<td>\n<p>13560</p>\n</td>\n</tr>\n<tr>\n<td>\n<p>Unpresented cheques</p>\n</td>\n<td>\n<p>5120</p>\n</td>\n</tr>\n<tr>\n<td>\n<p>Dividend received</p>\n</td>\n<td>2000</td>\n</tr>\n<tr>\n<td>\n<p>Uncredited cheque</p>\n</td>\n<td>2300</td>\n</tr>\n<tr>\n<td>\n<p>Bank charges</p>\n</td>\n<td>280</td>\n</tr>\n<tr>\n<td>\n<p>Standing order</p>\n</td>\n<td>600</td>\n</tr>\n<tr>\n<td>\n<p>Balance as per bank statement</p>\n</td>\n<td>?</td>\n</tr>\n</tbody>\n</table>",
        "explanation": "<p>BANK RECONCILIATION STATEMENT</p><p> </p><table border=\"1\" cellpadding=\"1\" cellspacing=\"1\">\n<tbody>\n<tr>\n<td> </td>\n<td>₦</td>\n<td>₦</td>\n</tr>\n<tr>\n<td>\n<p>Balance as per cashbook</p>\n</td>\n<td>\n<p> </p>\n</td>\n<td>\n<p>13560</p>\n</td>\n</tr>\n<tr>\n<td>\n<p>Unpresented cheques</p>\n</td>\n<td>\n<p>5120</p>\n</td>\n<td> </td>\n</tr>\n<tr>\n<td>\n<p>Dividend received</p>\n</td>\n<td>2000</td>\n<td>7120</td>\n</tr>\n<tr>\n<td>\n<p>Uncredited cheque</p>\n</td>\n<td>2300</td>\n<td> </td>\n</tr>\n<tr>\n<td>\n<p>Bank charges</p>\n</td>\n<td>280</td>\n<td> </td>\n</tr>\n<tr>\n<td>\n<p>Standing order</p>\n</td>\n<td>600</td>\n<td>3180</td>\n</tr>\n<tr>\n<td>\n<p>Balance as per bank statement</p>\n</td>\n<td> </td>\n<td>17500</td>\n</tr>\n</tbody>\n</table>",
        "correctIndex": 3,
        "options": [
            "₦10,740",
            "₦11,860",
            "₦16,380",
            "₦17,500"
        ],
        "type": "objectives"
    },
    {
        "course": "accounts",
        "institution": "jamb",
        "order": 50,
        "year": 2018,
        "question": "<p>Which of the following is not an inventory costing method?</p>",
        "explanation": null,
        "correctIndex": 3,
        "options": [
            "FIFO",
            "LIFO",
            "Average cost method",
            "LILA"
        ],
        "type": "objectives"
    },
    {
        "course": "accounts",
        "institution": "jamb",
        "order": 51,
        "year": 2018,
        "question": "<p>The major source of document which enables employer to calculate  the employee wages  is the?</p>",
        "explanation": "<p>The numbers of hours worked is the period of time that a person spends at paid labour. This means that, an employee pay roll is prepared by calculating the number of hours that employee spend working for his or her employer. The wages / salaries of that employee is subject to hourly rate. ( the more time you spend at work, the more the pay).</p><p>It is however worthy to note that, not all employees / employers practice this payment method.</p>",
        "correctIndex": 1,
        "options": [
            "norminal roll of employees",
            "records of number of hours worked",
            "effort of the employee",
            "Record of independence per employee"
        ],
        "type": "objectives"
    },
    {
        "course": "accounts",
        "institution": "jamb",
        "order": 52,
        "year": 2018,
        "question": "<p>The total credit sales for a period can be extracted from the?</p>",
        "explanation": "<p>The sales day book, also known as the sales book, is a <strong>ledger covering, in detail, all credit sales transactions during the day</strong>. These sales are then added together and recorded in the sales ledger for that day.</p>",
        "correctIndex": 1,
        "options": [
            "Cash book",
            "Sales day book",
            "Petty cash book",
            "Returns inwards"
        ],
        "type": "objectives"
    },
    {
        "course": "accounts",
        "institution": "jamb",
        "order": 53,
        "year": 2018,
        "question": "<p>If the scrap value is presently N15,000, what will be the yearly depreciation using the straight line method?</p>",
        "explanation": "<p>\\(35000 - 15000\\) = \\(20000 \\times\\frac{1}{5}\\)</p><p>= N4000</p>",
        "correctIndex": 0,
        "options": [
            "N4,000",
            "N7,000",
            "N11,000",
            "N24,000"
        ],
        "type": "objectives"
    },
    {
        "course": "accounts",
        "institution": "jamb",
        "order": 54,
        "year": 2018,
        "question": "<p>Mrs. Okoro who lives in the riverine community of Rivers State makes her living through crabbing and fishing. This type of occupation is? </p>",
        "explanation": "<p>Commercial farming occurs when a <strong>farm is set up for the sole purpose of producing crops and farm animals</strong> for sale, with the sole intention of making a profit. Commercial farms are often larger than regular family farms because economies of scale are richly sought after due to the immense competition involved.</p>",
        "correctIndex": 0,
        "options": [
            "commercial",
            "manufacturing",
            "service",
            "Extractive"
        ],
        "type": "objectives"
    },
    {
        "course": "accounts",
        "institution": "jamb",
        "order": 55,
        "year": 2018,
        "question": "<p>The yearly depreciation using the straight line method would be</p>",
        "explanation": "<p>35000 - 9000 = 26000</p><p>26000 * 1/5 = 5200</p>",
        "correctIndex": 2,
        "options": [
            "N8,800",
            "N6,500",
            "N5,200",
            "N4,400"
        ],
        "type": "objectives"
    },
    {
        "course": "accounts",
        "institution": "jamb",
        "order": 56,
        "year": 2018,
        "question": "<p>The accounting entries used to record a cheque issued by a business is to?</p>",
        "explanation": "<p>In posting accounting entries, always bear in mind the basic accounting principle of ''for every debit entry, there must be a corresponding credit entry''. In the above question, a business paid out money to its creditor (someone owed by the business) through a check, this means that, the business cash/bank accounts will be debited (take money from) while the drawer (creditor whom is owed by the business) will be credited. </p>",
        "correctIndex": 0,
        "options": [
            "debit cash book and credit drawer",
            "credit cash book and debit drawer",
            "debit cash book and credit suspense account",
            "credit cash book and debit suspense account"
        ],
        "type": "objectives"
    },
    {
        "course": "accounts",
        "institution": "jamb",
        "order": 57,
        "year": 2018,
        "question": "<p>In government accounting , the method used which records on the basis of financial entity with self balancing books instead of entity of propietorship is?</p>",
        "explanation": "<p>Fund accounting is an accounting system for recording resources whose use has been limited by the donor, grant authority, governing agency, or other individuals or organisations or by law. It emphasizes accountability rather than profitability, and is used by Nonprofit organizations and by governments. In this method, a fund consists of a self-balancing set of accounts and each are reported as either unrestricted, temporarily restricted or permanently restricted based on the provider-imposed restrictions.</p>",
        "correctIndex": 1,
        "options": [
            "virement",
            "fund accounting",
            "consolidated fund",
            "financial regulation"
        ],
        "type": "objectives"
    },
    {
        "course": "accounts",
        "institution": "jamb",
        "order": 58,
        "year": 2018,
        "question": "<p>which of the following  affects the accuracy and authenticity of trial balance? </p>",
        "explanation": "<p>Trial balance is prepared when transactions posted into the accounts are balanced up. The trial balance is then prepared to check the accuracy of those posted transaction. It is normal some times that some errors may be apparent but despite this, they may not affect the trial balance. It is very important for any accounting officer to note that these may occur in one way or another.</p><p><em><strong>A transposition error</strong></em> is simply substituting two sequential digits.Transposition errors are errors where figures (digits) are written in the wrong order in either a credit or a debit entry.This would create an imbalance between credits and debts, and so the error would be indicated by extracting a trial balance.For example, the number 78 for 87 or 1346 for 1436.</p>",
        "correctIndex": 2,
        "options": [
            "error of ommission",
            "error of commission",
            "error of transposition",
            "error of original entry"
        ],
        "type": "objectives"
    },
    {
        "course": "accounts",
        "institution": "jamb",
        "order": 59,
        "year": 2018,
        "question": "<p>The major advantages of an imprest system is that it ?</p>",
        "explanation": "<p>The<em><strong> imprest system</strong></em> is a form of financial accounting system. The most common imprest system is the petty cash system. The base characteristic of an imprest system is that a fixed amount is reserved, which after a certain period of time or when circumstances require, because money was spent, it will be replenished. This replenishment will come from another account source, e.g., petty cash will be replenished by cashing a cheque drawn on a bank account.</p><p>The advantages of using the Imprest system are versatility, accountability, practicality, limitation of theft, ease of use and limitation of expenditure. The system is a form of managing petty cash in a business. </p>",
        "correctIndex": 0,
        "options": [
            "ensures a proper accountability for every expenditure",
            "trains the young accountants in the preparation for greater responsibility",
            "relieves the chief cashier of the numerous petty cash payments",
            "serves as an analysis column for every expenses"
        ],
        "type": "objectives"
    },
    {
        "course": "accounts",
        "institution": "jamb",
        "order": 60,
        "year": 2018,
        "question": "<p>The value of the current assets will be?</p>",
        "explanation": "<p>The <strong>current assets </strong>is the summation of all balance sheet <strong>assets</strong> that can be converted to cash within one year or less. <strong>Current assets</strong> include cash, cash equivalents, inventory, accounts receivables, prepaid expenses, and marketable securities. From the above table, the following make up current assets; prepaid expenses + stock + debtors +cash balance. Hence we have;</p><p>current assets = 290+4,500+4,956+905= 10,651</p>",
        "correctIndex": 1,
        "options": [
            "N10,361",
            "N10,651",
            "N17,396",
            "N17,848"
        ],
        "type": "objectives"
    },
    {
        "course": "accounts",
        "institution": "jamb",
        "order": 61,
        "year": 2018,
        "question": "<p>Determine the current liabilities.</p>",
        "explanation": "<p>In accounting, current liabilities are often understood as all liabilities of the business that are to be settled in cash within the fiscal year or the operating cycle of a given firm, whichever period is longer. example </p><ul style=\"list-style-type:none\">\n<li>Accounts payable.</li>\n<li>Salaries payable.</li>\n<li>Short-term debt payable.</li>\n<li>Short-term notes payable.</li>\n<li>Current lease liability</li>\n</ul><p>From the table above, current liabilities = creditors + accruals expenses. Hence we have;</p><p>7,940+323= 8,263</p>",
        "correctIndex": 1,
        "options": [
            "N8,553",
            "N8,263",
            "N7,940",
            "N1,228"
        ],
        "type": "objectives"
    },
    {
        "course": "accounts",
        "institution": "jamb",
        "order": 62,
        "year": 2018,
        "question": "<p>The excess of sales over cost of goods sold is?</p>",
        "explanation": "<p>The gross profit formula is calculated by subtracting total cost of goods sold from total sales.Both the total sales and cost of goods sold are found on the income statement. <strong>Gross profit</strong> is a way to compare the cost of the goods your company sells and the income derived from those goods. It can be gotten as;</p><p><strong>Gross profit = total sales - cost of goods sold</strong></p>",
        "correctIndex": 1,
        "options": [
            "gross sales",
            "gross profit",
            "net profit",
            "net sales"
        ],
        "type": "objectives"
    },
    {
        "course": "accounts",
        "institution": "jamb",
        "order": 63,
        "year": 2018,
        "question": "<p>The control account is used in facilitating?</p>",
        "explanation": "<p>A control account, often called a controlling account, is a general ledger account that summarizes and combines all of the subsidiary accounts for a specific type. In other words, it’s a summary account that equals the sum of the subsidiary account and is used to simplify and organize the general ledger. The purpose of the control account is to keep the general ledger nice and clean without any details, yet contain the correct balances to be used in the financial statements. </p><ul style=\"list-style-type:disc\">\n<li>Control accounts allow a single trial balance to be extracted from the general ledger.</li>\n<li>If the trial balance does not balance, only the accounts whose control account does not reconcile need to be checked for errors.</li>\n<li>A different person can maintain the control account as a check against fraud.</li>\n<li>Control accounts speed up the process of producing management accounts information as the control account balance can be used without waiting for the individual balances to be reconciled and extracted.</li>\n<li>Control accounts reduce the amount of detail needed in the general ledger.</li>\n</ul>",
        "correctIndex": 0,
        "options": [
            "the various location of errors in the various accounts",
            "up to date bank transactions",
            "the payment of debts and liabilities of the firm",
            "assets distribution with respect to income"
        ],
        "type": "objectives"
    },
    {
        "course": "accounts",
        "institution": "jamb",
        "order": 64,
        "year": 2018,
        "question": "<p>The main objective of accounting report is to provide information about?</p>",
        "explanation": "<p>The accounting profession is no different. Foremost among the objectives of accounting and reporting is to provide useful information for investors, creditors, analysts, governments, and others. Accounting information is general purpose and should be designed to serve the information needs of all types of interested parties. The purpose of accounting is to accumulate and report on<strong><em> financial information about the performance, financial position, and cash flows of a business.</em></strong></p>",
        "correctIndex": 2,
        "options": [
            "the efficacy of assets",
            "a company's shareholding",
            "company's economic resources",
            "an entity's management"
        ],
        "type": "objectives"
    },
    {
        "course": "accounts",
        "institution": "jamb",
        "order": 65,
        "year": 2018,
        "question": "<p>from the data above, compute the prime cost. </p>",
        "explanation": "<p>Prime cost is the direct cost of a commodity in terms of the materials and labour involved in its production, excluding fixed costs. from the table above, prime cos is derivrd thus; <em><strong>Prime cost = direct material + direct labour + direct expenses </strong></em></p><p><strong>2,500+5,000+1,000=8,500</strong></p>",
        "correctIndex": 1,
        "options": [
            "N6,500",
            "N\t8,500",
            "N6,000",
            "N7,500"
        ],
        "type": "objectives"
    },
    {
        "course": "accounts",
        "institution": "jamb",
        "order": 66,
        "year": 2018,
        "question": "<p>calculate the sales ledger balance</p>",
        "explanation": "<p>The Sales Ledger is your record of sales, and whether or not you have received the money, and how much you are still owed. From the table above, it is derived as;  </p><p>sales opening balance - discount allowed - returns inwards + credit sales.<strong> 6,000 - 1,000 - 2,000 = 3,000 + 10,000 = 13,000</strong></p>",
        "correctIndex": 0,
        "options": [
            "N13,000",
            "N10,000",
            "N\t6,000",
            "N3,000"
        ],
        "type": "objectives"
    },
    {
        "course": "accounts",
        "institution": "jamb",
        "order": 67,
        "year": 2018,
        "question": "<p>what is the purchase ledger balance?</p>",
        "explanation": "<p>A <em>bought (purchase) ledger</em> is a system in accounting by which a business records and monitors its creditors. The <em>purchase ledger</em> contains the individual accounts of suppliers from whom the business has made <em>purchases</em> on credit. from the table above it is given as thus;</p><p>opening balance + credit purchase - returns outwards. ie, <strong>4,000 + 25000 = 29,000 - 6,000 = 23,000</strong></p>",
        "correctIndex": 3,
        "options": [
            "N29,000",
            "N24,000",
            "N4,000",
            "N23,000"
        ],
        "type": "objectives"
    },
    {
        "course": "accounts",
        "institution": "jamb",
        "order": 68,
        "year": 2018,
        "question": "<p>lubricating oil and spare parts of machines are example of?</p>",
        "explanation": "<p>To answer this question, we need to understand what the underlisted terms mean seperately. </p><p><strong>Direct materials</strong> are those <strong>materials and supplies that are consumed during the manufacture of a product</strong>, and which are directly identified with that product. Items designated as direct materials are usually listed in the bill of materials file for a product.<em><strong> example, when a car is being assembled from the manufacturing company, every material used up in assembling that car untill it gets to the consumer, is refered to as direct material.</strong></em></p><p><strong>Direct expense</strong> is an <strong>expense</strong> incurred that varies directly with changes in the volume of a cost object. A cost object is any item for which you are measuring <strong>expenses</strong>, such as products, product lines, services, sales regions, employees, and customers. ie, <em>Direct expenses</em> are costs that can be traced back to a specific department, often called an object, and are incurred only to benefit that department. <em><strong>Expenses connected with purchases of goods are known as direct expenses. that is to say, after the purchase of a machinery by a firm, the servicing and repairs of that machinery is an expenses incurred directly on the machine. </strong></em></p>",
        "correctIndex": 1,
        "options": [
            "indirect expense",
            "direct expense",
            "indirect material",
            "direct material"
        ],
        "type": "objectives"
    },
    {
        "course": "accounts",
        "institution": "jamb",
        "order": 69,
        "year": 2018,
        "question": "<p>for an incomplete record to provide necessary information, it must be converted to?</p>",
        "explanation": "<p>The Conversion Method of Single Entry System is a more scientific way of preparation of Final Accounts from Incomplete Records. It is also called the Transaction Approach. It does not furnish necessary <em>accounting information</em>. ... is a better approach for preparing accounts from <em>incomplete</em> records of transactions.</p>",
        "correctIndex": 1,
        "options": [
            "double entry",
            "single entry",
            "complete records",
            "statement of affairs"
        ],
        "type": "objectives"
    },
    {
        "course": "accounts",
        "institution": "jamb",
        "order": 70,
        "year": 2018,
        "question": "<p>The main difference between the ordinary and preference shareholders is that?</p>",
        "explanation": "<p><em><strong>An ordinary share defines a single unit of equity ownership of a corporation, where the holders of the ordinary shares receive the right to cast a vote in decisions involving important corporate matters</strong></em>. Such votes are available to each ordinary shareholder in correspondence to the number of ordinary shares held within the company. Ordinary shareholders are the last to receive dividends, and are only entitled to funds which remain after dividends on preferred shares are paid. Ordinary share holders may not receive dividend payments every year, and payments to ordinary shareholders depend on reinvestment decisions made by the company directors. In an event of the company facing liquidation, the ordinary shareholders will be the last to receive their share of funds, after the creditors and preference shareholders are paid. As such ordinary shares are riskier than bonds or preference shares. Ordinary shares are also referred to as ‘common stock’.</p><p>Preference shares are offered preference in relation to ordinary shares, where the preference shareholder receives dividends before ordinary shareholders are paid out. Preference shareholders are paid a fixed dividend and have the first claim on the assets and earnings. As such, preference shareholders receive their share of the firm’s residual value before ordinary shareholders in the event of liquidation. <em><strong>Preference shareholders do not have voting rights</strong></em>.</p>",
        "correctIndex": 0,
        "options": [
            "the former have voting rights while the latter do not",
            "in the case of winding up, the former are paid first before the latter",
            "the latter are not members of the company while the former are",
            "the former receives dividends while the latter do not"
        ],
        "type": "objectives"
    },
    {
        "course": "accounts",
        "institution": "jamb",
        "order": 71,
        "year": 2018,
        "question": "<p>A club received rent N10,000 and donation of N30,000. it paid N6,000 for entertainment and is still owing N16,000 . The balance of the receipts and payments account is?</p>",
        "explanation": "<p>income= N30,000 donation</p><p>expenditure= N10,000 rent + N6,000 entertainment= N16,000</p><p>income - expenditure = N30,000 - N16,000 = N14,000</p>",
        "correctIndex": 0,
        "options": [
            "N14,000",
            "N24,000",
            "N8,000",
            "N42,000"
        ],
        "type": "objectives"
    },
    {
        "course": "accounts",
        "institution": "jamb",
        "order": 72,
        "year": 2018,
        "question": "<p>The N6,000 subscription received is?</p>",
        "explanation": "<p>A <strong>subscription</strong> is a relatively new business model by which a customer agrees to pay the company for products or services throughout a specified time-period. For example, the customer may agree to purchase a one-year <strong>subscription</strong> to a magazine which he receives on a regular basis (monthly, weekly, etc.).</p><p><strong>Current liabilities </strong>are a company's debts or obligations that are due within one year or within a normal operating cycle. While <em><strong>current asset </strong></em>refers to cash and other assets that are expected to be converted to cash within a year. In this case, the company is owing a subscriber for a good or service that has already been paid for (by the subscriber), but not yet delivered by the company. <em><strong>on the part of the company's, it will be considered a liability due within a year  and on the subscriber' part, an asset due within a year. </strong></em></p>",
        "correctIndex": 2,
        "options": [
            "capital",
            "fixed asset",
            "current liability",
            "current asset"
        ],
        "type": "objectives"
    },
    {
        "course": "accounts",
        "institution": "jamb",
        "order": 73,
        "year": 2018,
        "question": "<p>what is the subscription to be charged to income and expenditure account?</p>",
        "explanation": "<p>An income and expenditure account is a record showing debits and credits for an organization within a particular time period. Income and expenditure accounts are also referred to as profit and loss accounts. Generally, these accounts are credited with debits and credits, whether paid or not. </p><p>the subscription to be charged to income and expenditure account = subscription for the year N30,000 + N6,000 subscrition for next year. ie, N36,000</p>",
        "correctIndex": 3,
        "options": [
            "N20,000",
            "N30,000",
            "N34,000",
            "N36,000"
        ],
        "type": "objectives"
    },
    {
        "course": "accounts",
        "institution": "jamb",
        "order": 74,
        "year": 2018,
        "question": "<p>A cash book had a opening balance of N15,200, closing balance of N18,400 and total cash received during the period of N36,000. What was the amount of cash paid out during the same period?</p>",
        "explanation": "<p>opening balance= N15,200</p><p>cash receipt = N36,000</p><p>closing balance= N18,400</p><p>N15,200 + N36,000 = N51,200</p><p>N51,200 - N18,400 = <strong>N32,800 (cash paid out)</strong></p>",
        "correctIndex": 2,
        "options": [
            "N29,200",
            "N17,800",
            "N32,800",
            "N19,600"
        ],
        "type": "objectives"
    },
    {
        "course": "accounts",
        "institution": "jamb",
        "order": 75,
        "year": 2018,
        "question": "<p>The current growth in the volume of trading and financial dealings in nigerian is helped by?</p>",
        "explanation": "<p>Financing activities are transactions or business events that affect long-term liabilities and equity. In other words, financing activities are transactions with creditors or investors used to fund either company operations or expansions. These transactions are the third set of cash activities displayed on the statement of cash flows.</p>",
        "correctIndex": 2,
        "options": [
            "credit as a factor in business",
            "payments for goods in cash",
            "increased financial activities",
            "government intervention"
        ],
        "type": "objectives"
    },
    {
        "course": "accounts",
        "institution": "jamb",
        "order": 76,
        "year": 2018,
        "question": "<p>when a bill is negotiated to a bank , it is said to be?</p>",
        "explanation": "<p>A bill discounting involves <strong>effectively selling a bill to a bank</strong> for an amount that is slightly less than the par value and before the maturity date associated with the bill of exchange.</p>",
        "correctIndex": 1,
        "options": [
            "accepted",
            "discounted",
            "surrendered",
            "cashed"
        ],
        "type": "objectives"
    },
    {
        "course": "accounts",
        "institution": "jamb",
        "order": 77,
        "year": 2018,
        "question": "<p>Bala ltd acquired the business of bello ltd and caused the separate existence of the latter company to terminate. </p>",
        "explanation": "<p>A merger is an agreement that unites two existing companies into one new company. There are several types of mergers and also several reasons why companies complete mergers. Mergers and <a href=\"https://www.investopedia.com/terms/a/acquisition.asp\">acquisitions</a> are commonly done to expand a company’s reach, expand into new segments, or gain market share. All of these are done to please shareholders and create value.</p><p>A merger is the voluntary fusion of two companies on broadly equal terms into one new legal entity. The firms that agree to merge are roughly equal in terms of size, customers, scale of operations, etc. For this reason, the term <strong>\"merger of equals\"</strong> is sometimes used. Acquisitions, unlike mergers, or generally not voluntary and involve one company actively purchasing another.</p><p>Mergers are most commonly done to gain <strong>market share</strong>, reduce costs of operations, expand to new territories, unite common products, grow revenues, and increase profits—all of which should benefit the firms' shareholders. After a merger, shares of the new company are distributed to existing shareholders of both original businesses.</p><p>Due to a large number of mergers, a<strong> mutual fund </strong>emerged, giving investors a chance to profit from merger deals. The fund captures the spread or amount left between the offer price and trading price. The Merger Fund from Westchester Capital Funds has been around since 1989. The fund invests in companies that have publicly announced a merger or takeover. To invest in the fund, a minimum amount of $2,000 is required, with a 1.91% <a href=\"https://www.investopedia.com/terms/e/expenseratio.asp\">expense ratio</a>. As of March 2, 2019, the fund has returned 6.1% annually since inception in 1989.</p>",
        "correctIndex": 2,
        "options": [
            "conversion",
            "dissolution",
            "merger",
            "absorption"
        ],
        "type": "objectives"
    },
    {
        "course": "accounts",
        "institution": "jamb",
        "order": 78,
        "year": 2018,
        "question": "<p>In order to make the cash book balance equal to the bank statement, it is usually to add?</p>",
        "explanation": "<p>we will look at the way in which a business deals with any differences between the balance of the bank account in the cash book and the closing balance of the bank account shown by the bank statement for the same period.<br>\nThese differences are explained by a document known as a bank reconciliation statement: which lists<br>\n• items which are in the cash book but not on the bank statement<br>\n• items which are on the bank statement but not in the cash book<br>\nThis process is an important one: it enables the business to update its cash book and also helps to prove the accuracy of the bookkeeping of the business and the bank.</p><p> 1 Prepare a Bank Reconciliation Statement<br>\n(a) Compare transactions that appear on both Cash Book and Bank Statement<br>\n(b) Update Cash Book from details of transactions appearing on Bank Statement<br>\n(c)  Balance the bank columns of the Cash Book to calculate the revised balance</p><p>2 Complete a Bank Reconciliation Statement<br>\n(a) Enter correct date of the statement<br>\n(b) Enter the balance at bank as per the Cash Book<br>\n(c) <strong><em>Enter details of unpresented cheques</em></strong><br>\n(d) Enter sub-total on reconciliation statement<br>\n(e) Enter details of bank lodgements<br>\n(f) Calculate balance as per Bank Statement</p>",
        "correctIndex": 3,
        "options": [
            "uncredited cheques",
            "direct payments by bank",
            "bank charged",
            "unpresented cheques"
        ],
        "type": "objectives"
    },
    {
        "course": "accounts",
        "institution": "jamb",
        "order": 79,
        "year": 2018,
        "question": "<p>The company's earnings yield is?</p>",
        "explanation": "<p>The earnings yield refers to the earnings per share for the most recent 12-month period divided by the current market price per share. The earnings yield (which is the inverse of the P/E ratio) shows the percentage of each dollar invested in the stock that was earned by the company.</p><p>EPS ÷ Market price</p><p>47/1.50 =  N31.33</p>",
        "correctIndex": 2,
        "options": [
            "N20.00%",
            "N25.00%",
            "N31.33%",
            "N39.17%"
        ],
        "type": "objectives"
    },
    {
        "course": "accounts",
        "institution": "jamb",
        "order": 80,
        "year": 2018,
        "question": "<p>what will be the price earnings ratio of the company?</p>",
        "explanation": "<p>Price-earnings ratio, also known as P/E ratio, is a tool that is used by investors to help decide whether they should buy a stock. Essentially, the P/E ratio tells potential investors how much they have to pay for every $1 of earnings. A low P/E ratio is attractive in the sense that one pays less for every $1 of earnings. At the same time, companies with higher P/E ratios generally expect higher earnings growth in the future than companies with low P/Es. it is gotten as:</p><p>Price earnings ratio = market value ÷ Earnings per share (EPS)</p><p>= \\(\\frac{1.5}{47K}\\)</p><p>= 3.19</p>",
        "correctIndex": 1,
        "options": [
            "N3.91",
            "N3.19",
            "N2.95",
            "N2.55"
        ],
        "type": "objectives"
    },
    {
        "course": "accounts",
        "institution": "jamb",
        "order": 81,
        "year": 2018,
        "question": "<p>The partnership deed normally specifies?</p>",
        "explanation": "<p>A partnership deed is a document containing an <strong>agreement that details the rights and obligations of each partner participating in a venture</strong>. For example, a deed of partnership could specify how proceeds from the partnership's business are to be divided among the partners.</p>",
        "correctIndex": 0,
        "options": [
            "how profits or losses are to be shared",
            "the capital to be contributed annually",
            "how salaries are paid to employees",
            "the profit that should be earned annually"
        ],
        "type": "objectives"
    },
    {
        "course": "accounts",
        "institution": "jamb",
        "order": 82,
        "year": 2018,
        "question": "<p>The accumulated fund of a non-trading concern can equally be referred to as?</p>",
        "explanation": "<p>An <strong>accumulated fund</strong> is the capital <strong>fund</strong> of a nonprofit organization. Money is directed into the <strong>accumulated fund</strong> when revenues are greater than expenditures and there is a budgetary surplus. Capital fund (also known as general fund and accumulated fund) is a balance sheet item which represents the surplus of assets over liabilities of a non-trading concerns. In other words, we can say that the capital fund of non-profit organizations is equivalent to the capital of for-profit organizations. It increases as a result of surplus and decreases as a result of deficit computed by preparing an income and expenditure account. </p>",
        "correctIndex": 2,
        "options": [
            "members equity",
            "share capital",
            "general fund",
            "surplus fund"
        ],
        "type": "objectives"
    },
    {
        "course": "accounts",
        "institution": "jamb",
        "order": 83,
        "year": 2018,
        "question": "<p>calculate the net profit. </p>",
        "explanation": "<p><strong>Net profit</strong>, also referred to as the bottom line, <em>net</em> income, or <em>net</em> earnings is a measure of the profitability of a venture after accounting for all costs and taxes. It is the actual <em>profit</em>, and includes the operating expenses that are excluded from gross <em>profit</em>. it represents the number of sales remaining after all operating expenses, interest, taxes and preferred stock dividends (but not common stock dividends) have been deducted from a company's total revenue. </p><p>net profit = gross profit - expenses</p><p>10,000 - 2500 = 7,500</p>",
        "correctIndex": 3,
        "options": [
            "N12,500",
            "N10,000",
            "N8,000",
            "N7,500"
        ],
        "type": "objectives"
    },
    {
        "course": "accounts",
        "institution": "jamb",
        "order": 84,
        "year": 2018,
        "question": "<p>what is the gross profit margin?</p>",
        "explanation": "<p><strong>Gross</strong> <strong>profit</strong> <strong>margin</strong> is a financial metric used to assess a company's financial health and business model by revealing the proportion of money left over from revenues after accounting for the cost of goods sold (COGS). <strong>Gross</strong> <strong>profit</strong> <strong>margin</strong>, also known as <strong>gross</strong> <strong>margin</strong>, is calculated by dividing <strong>gross</strong> <strong>profit</strong> by revenues. Also known as \"<strong>gross</strong> <strong>margin</strong>.\".</p><p>Gross Margin is generally calculated as the selling price of an item, less the cost of goods sold.</p><p>As a percentage, it can be calculated as:</p><p>Gross Margin (%) = (Revenue – Cost of goods sold) / Revenue * 100</p><p>revenue = 20,000</p><p>cogs = 10,000</p><p>20,000 - 10,000 = 10000 /20000 X 100 = 50%</p>",
        "correctIndex": 1,
        "options": [
            "100%",
            "50%",
            "40%",
            "30%"
        ],
        "type": "objectives"
    },
    {
        "course": "accounts",
        "institution": "jamb",
        "order": 85,
        "year": 2018,
        "question": "<p>Kakaku limited with three departments has a total of N7,200,000 as net debtors for the year ended 31/12/2106. The company's policy, provides for 15%bad debt annually. Which of the following represents the total balance of debtors before adjustment?</p>",
        "explanation": "<p>What is <strong>'Net Debt'?</strong>. Net debt shows a business's overall financial situation by subtracting the total value of its cash, cash equivalents, and other liquid assets, a process called netting. All the information necessary to determine a company's net debt can be found on its balance sheet.</p><p><strong>A bad debt </strong>is a monetary amount owed to a creditor that is unlikely to be paid and, or which the creditor is not willing to take action to collect for various reasons, often due to the debtor not having the money to pay, for example due to a company going into liquidation or insolvency.</p><p>net debtors = 7,200,000 (after all necessary deductions have been made)</p><p>bad debts = 15% ( an amount to be deducted from the total of all the debts owed to the company)</p><p><em><strong>The question says, ''the total balance of debtors before adjustment'' </strong></em>Remember net debtors is gotten after necessary deductions are made. This means that, the 15% provided as bad debts to be written off by the company, had already been deducted as well. to get the initial balance before the deductions, we simply get 15% of 7,200,000 and add it to the net debtors. Hence we have;</p><p><strong>15/100 * 7,200,000 = N1,080,000</strong></p><p><strong>7,200,000 + 1,080,000 = N8,280,000</strong></p>",
        "correctIndex": 0,
        "options": [
            "N6,120,000",
            "N8,280,000",
            "N6,120,300",
            "N8,820,000"
        ],
        "type": "objectives"
    },
    {
        "course": "accounts",
        "institution": "jamb",
        "order": 86,
        "year": 2018,
        "question": "<p>The basic role of accounting is to?</p>",
        "explanation": "<p>The role of accounting in business is to help internal and external stakeholders make better business decisions by providing them with financial information. This means that., the purpose of <strong>accounting</strong> is to accumulate and report on financial information about the performance, financial position, and cash flows of a business. This information is then used to reach decisions about how to manage the business, or invest in it, or lend money to it.</p>",
        "correctIndex": 2,
        "options": [
            "detect fraud",
            "attest to financial statements",
            "measure performance",
            "protect shareholders"
        ],
        "type": "objectives"
    },
    {
        "course": "accounts",
        "institution": "jamb",
        "order": 87,
        "year": 2018,
        "question": "<p>The fixed amount of money given to a petty cashier at the beginning of a period is called?</p>",
        "explanation": "<p>The word 'imprest' means 'advance amount' given to certain person to make petty payments. It is a system of petty cash book where a person (petty cashier) is given a fixed amount in the beginning of the month or week.</p>",
        "correctIndex": 0,
        "options": [
            "Imprest",
            "float",
            "cash advance",
            "cash"
        ],
        "type": "objectives"
    },
    {
        "course": "accounts",
        "institution": "jamb",
        "order": 88,
        "year": 2018,
        "question": "<p>A provision for bad debt account had N33,800 at the beginning of the year and N4,220 at the close of the year. If bad debts are calculated at the rate of 1/20% of annual credit sales, what was the credit sales for the period?</p>",
        "explanation": "<p>1/20 * 844400 = 4220</p>",
        "correctIndex": 1,
        "options": [
            "N210,000",
            "N844,400",
            "N840,000",
            "N500,000"
        ],
        "type": "objectives"
    }
]